velog_hits/__init__.py
velog_hits/command.py
velog_hits/convertor.py
velog_hits/crawler.py
velog_hits/graphql.py
velog_hits/main.py
velog_hits/html/__init__.py
velog_hits/html/base_html.py
velog_hits/html/creator.py
velog_hits/html/sorttable.js
velog_hits/html/table.css
velog_hits-1.0.0.dist-info/METADATA
velog_hits-1.0.0.dist-info/WHEEL
velog_hits-1.0.0.dist-info/entry_points.txt
velog_hits-1.0.0.dist-info/top_level.txt
velog_hits-1.0.0.dist-info/RECORD
