Metadata-Version: 2.1
Name: velog-hits
Version: 1.0.0
Summary: Velog Hits
Home-page: https://github.com/insutance/velog-hits
Author: insutance
Author-email: insutance@naver.com
License: UNKNOWN
Platform: UNKNOWN
Requires-Python: >= 3.8
Requires-Dist: pandas
Requires-Dist: requests
